eark_validator/__init__.py
eark_validator/const.py
eark_validator/mets.py
eark_validator/packages.py
eark_validator/rules.py
eark_validator/structure.py
eark_validator/utils.py
eark_validator/cli/__init__.py
eark_validator/cli/app.py
eark_validator/infopacks/__init__.py
eark_validator/infopacks/information_package.py
eark_validator/infopacks/manifest.py
eark_validator/infopacks/package_handler.py
eark_validator/ipxml/__init__.py
eark_validator/ipxml/namespaces.py
eark_validator/ipxml/schema.py
eark_validator/ipxml/schematron.py
eark_validator/ipxml/resources/profiles/V2.0.4/E-ARK-CSIP.xml
eark_validator/ipxml/resources/profiles/V2.0.4/E-ARK-DIP.xml
eark_validator/ipxml/resources/profiles/V2.0.4/E-ARK-SIP.xml
eark_validator/ipxml/resources/profiles/V2.1.0/E-ARK-CSIP.xml
eark_validator/ipxml/resources/profiles/V2.1.0/E-ARK-DIP.xml
eark_validator/ipxml/resources/profiles/V2.1.0/E-ARK-SIP.xml
eark_validator/ipxml/resources/schema/DILCISExtensionMETS.xsd
eark_validator/ipxml/resources/schema/DILCISExtensionSIPMETS.xsd
eark_validator/ipxml/resources/schema/mets.csip.local.v2-0.xsd
eark_validator/ipxml/resources/schema/mets.profile.local.v2-0.xsd
eark_validator/ipxml/resources/schema/mets.profile.v2-0.xsd
eark_validator/ipxml/resources/schema/mets.sip.local.v2-0.xsd
eark_validator/ipxml/resources/schema/mets.xsd
eark_validator/ipxml/resources/schema/xhtml1-strict.xsd
eark_validator/ipxml/resources/schema/xlink.xsd
eark_validator/ipxml/resources/schema/xml.xsd
eark_validator/ipxml/resources/schematron/V2.0.4/CSIP/mets_amdSec_rules.xml
eark_validator/ipxml/resources/schematron/V2.0.4/CSIP/mets_behaviorSec_rules.xml
eark_validator/ipxml/resources/schematron/V2.0.4/CSIP/mets_dmdSec_rules.xml
eark_validator/ipxml/resources/schematron/V2.0.4/CSIP/mets_fileSec_rules.xml
eark_validator/ipxml/resources/schematron/V2.0.4/CSIP/mets_metsHdr_rules.xml
eark_validator/ipxml/resources/schematron/V2.0.4/CSIP/mets_metsRootElement_rules.xml
eark_validator-1.1.3.dist-info/LICENSE
eark_validator-1.1.3.dist-info/METADATA
eark_validator-1.1.3.dist-info/WHEEL
eark_validator-1.1.3.dist-info/entry_points.txt
eark_validator-1.1.3.dist-info/top_level.txt
eark_validator-1.1.3.dist-info/RECORD
