Metadata-Version: 2.1
Name: eark-validator
Version: 1.1.3
Summary: E-ARK Python Information Package Validation
Author-email: E-ARK Foundation <admin@e-ark-foundation.eu>
Maintainer-email: E-ARK Foundation <admin@e-ark-foundation.eu>, Carl Wilson <carl@openpreservation.org>
License: 
Project-URL: Homepage, https://www.e-ark-foundation.eu/e-ark-software-py-e-ark-ip-validator/
Project-URL: Issues, https://github.com/E-ARK-Software/eark-validator/issues
Project-URL: Repository, https://github.com/E-ARK-Software/eark-validator.git
Classifier: Programming Language :: Python :: 3
Classifier: License :: OSI Approved :: Apache Software License
Classifier: Operating System :: OS Independent
Requires-Python: >=3.10
License-File: LICENSE
Requires-Dist: lxml ==5.1.0
Requires-Dist: importlib-resources ==5.12.0
Requires-Dist: pydantic <3.0.0,>=2.5.3
Provides-Extra: testing
Requires-Dist: pre-commit ; extra == 'testing'
Requires-Dist: pytest ; extra == 'testing'
Requires-Dist: pylint ; extra == 'testing'
Requires-Dist: pytest-cov ; extra == 'testing'
Requires-Dist: pytest-runner ; extra == 'testing'
